{
  "name": "2010-2014.commerce.gov",
  "initial_url": "https://2010-2014.commerce.gov",
  "initial_domain": "2010-2014.commerce.gov",
  "initial_base_domain": "commerce.gov",
  "initial_top_level_domain": "gov",
  "redirect": false,
  "url": "https://2010-2014.commerce.gov/",
  "domain": "2010-2014.commerce.gov",
  "base_domain": "commerce.gov",
  "top_level_domain": "gov",
  "live": false,
  "filter": false,
  "status_code": 403,
  "media_type": "text/html",
  "agency": "Department of Commerce",
  "bureau": "Department of Commerce",
  "branch": "Executive",
  "404_test": false,
  "source_list": [
    "pulse",
    "omb_idea",
    "other",
    "final_url_websites",
    "cisa"
  ],
  "primary_scan_status": "completed",
  "accessibility_scan_status": "completed",
  "dns_scan_status": "completed",
  "not_found_scan_status": "completed",
  "performance_scan_status": "completed",
  "robots_txt_scan_status": "completed",
  "security_scan_status": "completed",
  "sitemap_xml_scan_status": "completed",
  "www_scan_status": "dns_resolution_error",
  "page_hash": "6de32edd3e321df5d29bf9f8f62d70a4",
  "accessibility_violations": "{\"auto-updating\":1}",
  "pageviews": null,
  "visits": null,
  "ipv6": true,
  "hostname": null,
  "cms": null,
  "login_provider": null,
  "login": null,
  "site_search": false,
  "search_dot_gov": null,
  "dap": false,
  "dap_parameters": "",
  "dap_version": "",
  "ga_tag_id": "G-guQAgb5pSt,G-wPid,G-LdcCELXAInd1VkJ",
  "third_party_service_domains": [
    "challenges.cloudflare.com",
    "static.cloudflareinsights.com"
  ],
  "third_party_service_urls": [
    "https://challenges.cloudflare.com/cdn-cgi/challenge-platform/h/b/cmg/1",
    "https://challenges.cloudflare.com/cdn-cgi/challenge-platform/h/b/d/94c00eaa489ca60a/1749298341709/4_hZlb4qs2QoZt2",
    "https://challenges.cloudflare.com/cdn-cgi/challenge-platform/h/b/flow/ov1/1058463329:1749295035:m_bat9uYxL6-0YXbDE3KWoZPkS8i1h3T19ajYFbdzy0/94c00eaa489ca60a/QXxymk1VyeZMAYMw6r76iQ2LgsAkjudYdZkJzE5rVz4-1749298341-1.2.1.1-8OHzZwx5YYfaOSferrGsvvxloZ8ATC6KVFXn85_grroCKcG43KyXFdMffWYpRZ4N",
    "https://challenges.cloudflare.com/cdn-cgi/challenge-platform/h/b/orchestrate/chl_api/v1",
    "https://challenges.cloudflare.com/cdn-cgi/challenge-platform/h/b/pat/94c00eaa489ca60a/1749298341707/e6aa64819a2b21da49c7e99789e86d55d5a3c4420ecf303d9a8fde3ceaf510f5/EskaYLtDT92i-ZD",
    "https://challenges.cloudflare.com/turnstile/v0/b/f9574c83b4d7/api.js",
    "https://static.cloudflareinsights.com/beacon.min.js/vcd15cbe7772f49c399c6a5babf22c1241717689176015"
  ],
  "third_party_service_count": 2,
  "cookie_domains": [
    ".commerce.gov"
  ],
  "viewport_meta_tag": true,
  "required_links_url": null,
  "required_links_text": null,
  "https_enforced": true,
  "hsts": true,
  "title": "Just a moment...",
  "description": null,
  "keywords": null,
  "og_title": null,
  "og_description": null,
  "og_article_published": null,
  "og_article_modified": null,
  "og_image": null,
  "og_type": null,
  "og_url": null,
  "canonical_link": null,
  "language": "en-US",
  "language_link": "",
  "main_element_present": false,
  "robots_txt_detected": false,
  "robots_txt_url": "https://2010-2014.commerce.gov/robots.txt",
  "robots_txt_status_code": 403,
  "robots_txt_media_type": "text/html",
  "robots_txt_filesize": 61654,
  "robots_txt_crawl_delay": null,
  "robots_txt_sitemap_locations": null,
  "sitemap_xml_detected": false,
  "sitemap_xml_url": "https://2010-2014.commerce.gov/sitemap.xml",
  "sitemap_xml_status_code": 403,
  "sitemap_xml_media_type": "text/html",
  "sitemap_xml_filesize": 61147,
  "sitemap_xml_count": 0,
  "sitemap_xml_lastmod": null,
  "sitemap_xml_pdf_count": 0,
  "sitemap_xml_page_hash": "04946b0f5e219ae79f11754ca3e2f665",
  "uswds_favicon": 0,
  "uswds_favicon_in_css": 0,
  "uswds_publicsans_font": 0,
  "uswds_inpage_css": 0,
  "uswds_usa_class_list": null,
  "uswds_banner_heres_how": false,
  "uswds_usa_classes": 0,
  "uswds_string": 0,
  "uswds_string_in_css": 0,
  "uswds_semantic_version": null,
  "uswds_version": 0,
  "uswds_count": 0,
  "www_url": null,
  "www_status_code": null,
  "www_title": null
}