{
  "name": null,
  "initial_url": "https://beowulf.pppl.gov",
  "initial_domain": "beowulf.pppl.gov",
  "initial_base_domain": "pppl.gov",
  "initial_top_level_domain": "gov",
  "redirect": null,
  "url": null,
  "domain": null,
  "base_domain": null,
  "top_level_domain": null,
  "live": null,
  "filter": false,
  "status_code": null,
  "media_type": null,
  "agency": "Department of Energy",
  "bureau": "Princeton Plasma Physics Lab",
  "branch": "Executive",
  "404_test": false,
  "source_list": [
    "pulse",
    "cisa"
  ],
  "public": null,
  "primary_scan_status": "execution_context_destroyed",
  "accessibility_scan_status": "execution_context_destroyed",
  "dns_scan_status": "completed",
  "not_found_scan_status": "completed",
  "performance_scan_status": "execution_context_destroyed",
  "robots_txt_scan_status": "completed",
  "security_scan_status": "unknown_error",
  "sitemap_xml_scan_status": "completed",
  "www_scan_status": "dns_resolution_error",
  "page_hash": null,
  "accessibility_violations": null,
  "ipv6": true,
  "hostname": null,
  "cms": null,
  "login_provider": null,
  "login": null,
  "site_search": null,
  "search_dot_gov": null,
  "dap": null,
  "dap_parameters": null,
  "dap_version": "",
  "ga_tag_id": "",
  "third_party_service_domains": null,
  "third_party_service_urls": null,
  "third_party_service_count": null,
  "cookie_domains": null,
  "viewport_meta_tag": null,
  "required_links_url": null,
  "required_links_text": null,
  "https_enforced": null,
  "hsts": null,
  "title": "Sign In",
  "description": null,
  "keywords": null,
  "og_title": null,
  "og_description": null,
  "og_article_published": null,
  "og_article_modified": null,
  "og_image": null,
  "og_type": null,
  "og_url": null,
  "canonical_link": null,
  "language": null,
  "language_link": null,
  "main_element_present": null,
  "robots_txt_detected": false,
  "robots_txt_url": "https://sso.pppl.gov/adfs/ls/?SAMLRequest=jZJNb9swDIbv%2BRWF7rZUp8kSIQmQNe0WIEuCJuuhl0G26VaATWki3W7%2Ffv7o9yEYbyL5vHhfQjMyVen1suYHvIHfNRAPzpr6U5VIuhvORR1QO0OWNJoKSHOmD8sfG53ESvvg2GWuFJ%2Bw05QhgsDWYY%2BtV3Ox215tdt%2FW219FPkmnZjSGQg1HoLKLbDqcKDDn4zSfJMn0osjT6SQ1PXoLgRqduWhkxaBXI6phjcQGuemrZBSpYaSSo%2Fqi1bkeje96dNWEtWi4wx%2BYPWkpiVzsvS%2Fje%2FcoTV6QLEn2%2B%2FvnqF8t5hbvTydM%2ByXS34%2FHfbTfHY69yPIl%2BaVDqisIBwiPNoOfN5s3E62ByCIHg8CxDxYzYIcx5LVsjytNRmLR6c3at%2B4ih8V%2F8V4iPEXNWYYz%2BR5%2Bk%2FN62%2BRZr%2FautNnfrt%2FWtQuV4dOx247No6Jb1a0BsoAsXkWWZemeLgMYhrngUIM4k4tB7%2BTjP1z8Aw%3D%3D&RelayState=https%3A%2F%2Fpppl-intranet.princeton.edu%2Fdepartments%2Fcomputing-and-information-technology%2Fresearch-computing&SigAlg=http%3A%2F%2Fwww.w3.org%2F2001%2F04%2Fxmldsig-more%23rsa-sha256&Signature=NmUsRP9aVOPoq6717IxTUzMfgEQ123EytGXO4EMEY5jDYgUPzQfKp3trwL1W6MTaE9PtEji9Z%2FkcD0LkfFfLm4%2BK4OkonZvfVnaNhfZ6oa2uU%2FU5RmunwiavFc3yzoJ2wqJR%2FMArQj9twZs4bmmb34pKmrAqUFUgIE2PNelt%2B0FjDswgWV2VGNGPY8EBBdy95ZXGRQRt%2By%2BcACA3j%2BL3KoiQSETOrpsWY%2BHuzHprKSeKBREuGG7Q%2B7s2adB0HIBUiCKS9AragH4o%2BnJIIOufYYs5Y4EbNXOCodzN2Cw4rmisOS7QyHv05XWO5Wr2IQSTw5be4MBhn9Uc9zauuo%2F%2BXQ%3D%3D",
  "robots_txt_status_code": 200,
  "robots_txt_media_type": "text/html",
  "robots_txt_filesize": null,
  "robots_txt_crawl_delay": null,
  "robots_txt_sitemap_locations": null,
  "sitemap_xml_detected": false,
  "sitemap_xml_url": "https://sso.pppl.gov/adfs/ls/?SAMLRequest=jZJNb9swDIbv%2BRWF7rZsp403IQmQNVsbIEuCJuuhl0GR6VaATaki3Y9%2FP3%2B067ZDMN5E8nnxvoSmpOvKq0XDD3gDjw0Qj87aeqkrJNUPZ6IJqJwmSwp1DaTYqP3i%2B1plcaJ8cOyMq8Q%2F2GlKE0Fg63DAVsuZ2G6%2BrrdXq83PSTYxKXw66nFZpOnRnGv9OS%2FHpcnLDPK0TPN8YorsfEBvIVCrMxOtrBgNakQNrJBYI7f9JLuIknGUZIckV0mqLvK7AV22YS1q7vEHZk9KSiIXe%2B%2Br%2BN49SV2UJCuSw%2F7uLeoXi4XF%2B9MJj8MSqevDYRfttvvDILJ4T37pkJoawh7CkzXw42b9YaIzEFnkoBE49sGiAXYYQ9HI7rhSGxLzXm%2FavVUfOcz%2Fi%2FcS4TlqzzKeyj%2FhDzmvNm2e1XLnKmte%2B35X31yoNZ%2BO3XVsEZX9quoMkAVk8VtkUVXu%2BTKAZpgJDg2IMzkfDU7%2B%2FofzXw%3D%3D&RelayState=https%3A%2F%2Fpppl-intranet.princeton.edu%2Fdepartments%2Fcomputing-and-information-technology%2Fresearch-computing&SigAlg=http%3A%2F%2Fwww.w3.org%2F2001%2F04%2Fxmldsig-more%23rsa-sha256&Signature=S3dPb1wQ9k9%2BOfRcBW%2BivIVElGeKMpkIvisIuZReFsch%2Bl3vfSYavAAjnnzfAc%2FOuRDayiB9REwFZK6aq54%2FjS1ZObV8z6wFZNwIoZaswxl2sVrMSJNnog%2BZ57jiqiXs2CNS8jndyrdGUQF3y%2BXpxzR0%2FmFg3sLeOloSYjFO%2BfMuP7ibZXQrfDKNTZDJ1eQ6wDBrI2slb7fR%2FyB%2F3Zs9eDiGI9%2BfCa09bKwDLkWKHpZchJciXgLJs6eAjzRbSJpIHjpUwrQUt3iSZNeN7GG3KB%2FoL%2BbdR0ODpZBmB12qaBTlz6N%2FftflFfWxteSshLNVENw1Ph23umhODvzFgI0Nlw%3D%3D",
  "sitemap_xml_status_code": 200,
  "sitemap_xml_media_type": "text/html",
  "sitemap_xml_filesize": null,
  "sitemap_xml_count": null,
  "sitemap_xml_lastmod": null,
  "sitemap_xml_pdf_count": null,
  "sitemap_xml_page_hash": null,
  "uswds_favicon": null,
  "uswds_favicon_in_css": null,
  "uswds_publicsans_font": null,
  "uswds_inpage_css": null,
  "uswds_usa_class_list": null,
  "uswds_banner_heres_how": null,
  "uswds_usa_classes": null,
  "uswds_string": null,
  "uswds_string_in_css": null,
  "uswds_semantic_version": null,
  "uswds_version": null,
  "uswds_count": null,
  "www_url": null,
  "www_status_code": null,
  "www_title": null
}