{
  "name": "ci.noaa.gov",
  "initial_url": "https://ci.noaa.gov",
  "initial_domain": "ci.noaa.gov",
  "initial_base_domain": "noaa.gov",
  "initial_top_level_domain": "gov",
  "redirect": false,
  "url": "https://ci.noaa.gov/",
  "domain": "ci.noaa.gov",
  "base_domain": "noaa.gov",
  "top_level_domain": "gov",
  "live": true,
  "filter": false,
  "status_code": 200,
  "media_type": "text/html",
  "agency": "Department of Commerce",
  "bureau": "National Oceanic and Atmospheric Administration",
  "branch": "Executive",
  "404_test": false,
  "source_list": [
    "pulse",
    "omb_idea",
    "other",
    "final_url_websites",
    "cisa"
  ],
  "public": true,
  "primary_scan_status": "completed",
  "accessibility_scan_status": "completed",
  "dns_scan_status": "completed",
  "not_found_scan_status": "completed",
  "performance_scan_status": "completed",
  "robots_txt_scan_status": "completed",
  "security_scan_status": "completed",
  "sitemap_xml_scan_status": "completed",
  "www_scan_status": "dns_resolution_error",
  "page_hash": "8d19ea985cc73190c7d1e25e957642e4",
  "accessibility_violations": "{\"contrast\":12}",
  "pageviews": null,
  "visits": null,
  "ipv6": true,
  "hostname": "cloudfront.net",
  "cms": "WordPress",
  "login_provider": null,
  "login": [
    "\"password\"",
    "type=\"password\""
  ],
  "site_search": true,
  "search_dot_gov": null,
  "dap": false,
  "dap_parameters": "",
  "dap_version": "",
  "ga_tag_id": "",
  "third_party_service_domains": [
    "cdnjs.cloudflare.com",
    "ci.dev-wordpress-oarhq.woc.noaa.gov",
    "fonts.googleapis.com",
    "www.googletagmanager.com"
  ],
  "third_party_service_urls": [
    "https://cdnjs.cloudflare.com/ajax/libs/uswds/3.3.0/css/uswds.min.css",
    "https://cdnjs.cloudflare.com/ajax/libs/uswds/3.3.0/fonts/source-sans-pro/sourcesanspro-bold-webfont.woff2",
    "https://cdnjs.cloudflare.com/ajax/libs/uswds/3.3.0/fonts/source-sans-pro/sourcesanspro-regular-webfont.woff2",
    "https://cdnjs.cloudflare.com/ajax/libs/uswds/3.3.0/img/usa-icons/expand_more.svg",
    "https://cdnjs.cloudflare.com/ajax/libs/uswds/3.3.0/js/uswds-init.min.js",
    "https://cdnjs.cloudflare.com/ajax/libs/uswds/3.3.0/js/uswds.min.js",
    "https://ci.dev-wordpress-oarhq.woc.noaa.gov/wp-content/uploads/2022/04/email.png",
    "https://fonts.googleapis.com/css",
    "https://www.googletagmanager.com/gtag/js"
  ],
  "third_party_service_count": 4,
  "cookie_domains": [
    ".noaa.gov"
  ],
  "viewport_meta_tag": true,
  "required_links_url": [
    "foia",
    "privacy",
    "usa.gov"
  ],
  "required_links_text": [
    "accessibility",
    "foia",
    "usa.gov"
  ],
  "https_enforced": true,
  "hsts": false,
  "title": "Home - Cooperative Institutes",
  "description": "Cooperative Institutes are academic and non-profit research institutions that demonstrate the highest level of performance and conduct research that supports NOAA’s Mission Goals and Strategic Plan.",
  "keywords": null,
  "og_title": "Home - Cooperative Institutes",
  "og_description": "Cooperative Institutes are academic and non-profit research institutions that demonstrate the highest level of performance and conduct research that supports NOAA’s Mission Goals and Strategic Plan.",
  "og_article_published": null,
  "og_article_modified": "2023-09-29T19:49:11.000Z",
  "og_image": null,
  "og_type": "website",
  "og_url": "/",
  "canonical_link": "/",
  "language": "en-US",
  "language_link": "",
  "main_element_present": true,
  "robots_txt_detected": false,
  "robots_txt_url": "https://ci.noaa.gov/robots.txt",
  "robots_txt_status_code": 404,
  "robots_txt_media_type": "text/html",
  "robots_txt_filesize": null,
  "robots_txt_crawl_delay": null,
  "robots_txt_sitemap_locations": null,
  "sitemap_xml_detected": true,
  "sitemap_xml_url": "https://ci.noaa.gov/sitemap.xml",
  "sitemap_xml_status_code": 200,
  "sitemap_xml_media_type": "text/xml",
  "sitemap_xml_filesize": 743,
  "sitemap_xml_count": 0,
  "sitemap_xml_lastmod": "2025-04-24T18:34:55.000Z",
  "sitemap_xml_pdf_count": 0,
  "sitemap_xml_page_hash": "1b8c94667fa4c6eef1810c509c254d20",
  "uswds_favicon": 20,
  "uswds_favicon_in_css": 0,
  "uswds_publicsans_font": 0,
  "uswds_inpage_css": 0,
  "uswds_usa_class_list": [
    "usa-accordion",
    "usa-banner"
  ],
  "uswds_banner_heres_how": true,
  "uswds_banner_heres_how-2": true,
  "uswds_usa_classes": 20,
  "uswds_string": 8,
  "uswds_string_in_css": 20,
  "uswds_semantic_version": "v3.3.0",
  "uswds_version": 100,
  "uswds_count": 168,
  "www_url": null,
  "www_status_code": null,
  "www_title": null
}