{
  "name": "datasearch.globe.gov",
  "initial_url": "https://datasearch.globe.gov",
  "initial_domain": "datasearch.globe.gov",
  "initial_base_domain": "globe.gov",
  "initial_top_level_domain": "gov",
  "redirect": false,
  "url": "https://datasearch.globe.gov/",
  "domain": "datasearch.globe.gov",
  "base_domain": "globe.gov",
  "top_level_domain": "gov",
  "live": true,
  "filter": false,
  "status_code": 200,
  "media_type": "text/html",
  "agency": "National Aeronautics and Space Administration",
  "bureau": "NASA Science Data Systems Branch",
  "branch": "Executive",
  "404_test": true,
  "source_list": [
    "dap",
    "pulse",
    "omb_idea",
    "other",
    "final_url_websites",
    "cisa"
  ],
  "public": null,
  "primary_scan_status": "completed",
  "accessibility_scan_status": "completed",
  "dns_scan_status": "completed",
  "not_found_scan_status": "completed",
  "performance_scan_status": "completed",
  "robots_txt_scan_status": "completed",
  "security_scan_status": "completed",
  "sitemap_xml_scan_status": "completed",
  "www_scan_status": "dns_resolution_error",
  "page_hash": "07ef1e8ff7600410e47c6f32f7191d92",
  "accessibility_violations": "{\"frames-iframes\":1,\"language\":1}",
  "pageviews": 605,
  "visits": 553,
  "ipv6": true,
  "hostname": "amazonaws.com",
  "cms": null,
  "login_provider": null,
  "login": null,
  "site_search": false,
  "search_dot_gov": null,
  "dap": true,
  "dap_parameters": {
    "agency": "NASA",
    "subagency": "Center"
  },
  "dap_version": "20250212 v8.6 - GA4",
  "ga_tag_id": "G-CSLL4ZEK4L,G-LQVHLZY5R2,G-C3QT1VQCR4",
  "third_party_service_domains": [
    "a.tile.openstreetmap.org",
    "ajax.googleapis.com",
    "api.appzi.io",
    "b.tile.openstreetmap.org",
    "c.tile.openstreetmap.org",
    "dap.digitalgov.gov",
    "dev.virtualearth.net",
    "fonts.googleapis.com",
    "fonts.gstatic.com",
    "translate-pa.googleapis.com",
    "translate.google.com",
    "translate.googleapis.com",
    "vis.globe.gov",
    "w.appzi.io",
    "www.google-analytics.com",
    "www.google.com",
    "www.googletagmanager.com",
    "www.gstatic.com"
  ],
  "third_party_service_urls": [
    "https://a.tile.openstreetmap.org/2/0/2.png",
    "https://a.tile.openstreetmap.org/2/1/0.png",
    "https://a.tile.openstreetmap.org/3/0/2.png",
    "https://a.tile.openstreetmap.org/3/1/1.png",
    "https://a.tile.openstreetmap.org/3/1/4.png",
    "https://a.tile.openstreetmap.org/3/2/3.png",
    "https://a.tile.openstreetmap.org/3/3/2.png",
    "https://ajax.googleapis.com/ajax/libs/jquery/3.6.1/jquery.min.js",
    "https://ajax.googleapis.com/ajax/libs/jqueryui/1.13.2/jquery-ui.min.js",
    "https://ajax.googleapis.com/ajax/libs/jqueryui/1.13.2/themes/smoothness/jquery-ui.css",
    "https://api.appzi.io/api/probe/SpDNC",
    "https://b.tile.openstreetmap.org/1/0/1.png",
    "https://b.tile.openstreetmap.org/2/0/1.png",
    "https://b.tile.openstreetmap.org/2/1/2.png",
    "https://b.tile.openstreetmap.org/3/0/1.png",
    "https://b.tile.openstreetmap.org/3/0/4.png",
    "https://b.tile.openstreetmap.org/3/1/3.png",
    "https://b.tile.openstreetmap.org/3/2/2.png",
    "https://b.tile.openstreetmap.org/3/3/1.png",
    "https://b.tile.openstreetmap.org/3/3/4.png",
    "https://c.tile.openstreetmap.org/0/0/0.png",
    "https://c.tile.openstreetmap.org/1/0/0.png",
    "https://c.tile.openstreetmap.org/2/0/0.png",
    "https://c.tile.openstreetmap.org/2/1/1.png",
    "https://c.tile.openstreetmap.org/3/0/3.png",
    "https://c.tile.openstreetmap.org/3/1/2.png",
    "https://c.tile.openstreetmap.org/3/2/1.png",
    "https://c.tile.openstreetmap.org/3/2/4.png",
    "https://c.tile.openstreetmap.org/3/3/3.png",
    "https://dap.digitalgov.gov/Universal-Federated-Analytics-Min.js",
    "https://dap.digitalgov.gov/web-vitals/dist/web-vitals.attribution.iife.js",
    "https://dev.virtualearth.net/REST/v1/Imagery/Metadata/Aerial",
    "https://dev.virtualearth.net/REST/v1/Imagery/Metadata/AerialWithLabels",
    "https://dev.virtualearth.net/REST/v1/Imagery/Metadata/Road",
    "https://fonts.googleapis.com/icon",
    "https://fonts.gstatic.com/s/i/productlogos/translate/v14/24px.svg",
    "https://fonts.gstatic.com/s/materialicons/v143/flUhRq6tzZclQEJ-Vdg-IuiaDsNcIhQ8tQ.woff2",
    "https://translate-pa.googleapis.com/v1/supportedLanguages",
    "https://translate.google.com/translate_a/element.js",
    "https://translate.googleapis.com/_/translate_http/_/js/k=translate_http.tr.en_US.wX7qQ5EH6oI.O/am=ACA/d=1/exm=el_conf/ed=1/rs=AN8SPfrNtUAtY-e6eilwMrQxoU8LiA-1Hg/m=el_main",
    "https://translate.googleapis.com/translate_static/img/te_ctrl3.gif",
    "https://vis.globe.gov/GLOBE/DataTypeDef",
    "https://vis.globe.gov/GLOBE/GLOBElookup",
    "https://vis.globe.gov/GLOBE/ProtocolBundle.json",
    "https://vis.globe.gov/GLOBE/ScienceDataService",
    "https://vis.globe.gov/GLOBE/css/ADATinterface.css",
    "https://vis.globe.gov/GLOBE/css/VISinterface.css",
    "https://vis.globe.gov/GLOBE/css/dhtmlxGrid.css",
    "https://vis.globe.gov/GLOBE/css/font-awesome.min.css",
    "https://vis.globe.gov/GLOBE/css/jquery-ui-1.13.2.custom/images/ui-bg_highlight-soft_75_6296cf_1x100.png",
    "https://vis.globe.gov/GLOBE/css/jquery-ui-1.13.2.custom/jquery-ui.min.css",
    "https://vis.globe.gov/GLOBE/css/popupContents.css",
    "https://vis.globe.gov/GLOBE/css/selector.css",
    "https://vis.globe.gov/GLOBE/css/socialshare.css",
    "https://vis.globe.gov/GLOBE/css/style.css",
    "https://vis.globe.gov/GLOBE/fonts/fontawesome-webfont.woff",
    "https://vis.globe.gov/GLOBE/images/Science_legendbutton.png",
    "https://vis.globe.gov/GLOBE/images/adat_welcome_pic.jpg",
    "https://vis.globe.gov/GLOBE/images/ajax-loader.gif",
    "https://vis.globe.gov/GLOBE/images/blank-check.png",
    "https://vis.globe.gov/GLOBE/images/blkX.svg",
    "https://vis.globe.gov/GLOBE/images/blkfacebook.svg",
    "https://vis.globe.gov/GLOBE/images/blkpin.svg",
    "https://vis.globe.gov/GLOBE/images/blue-share-icon.png",
    "https://vis.globe.gov/GLOBE/images/countlegend-top.jpg",
    "https://vis.globe.gov/GLOBE/images/datacounts-icon-unsel.png",
    "https://vis.globe.gov/GLOBE/images/draw-region-off.png",
    "https://vis.globe.gov/GLOBE/images/dv_air_temp_dailies_current_temp_measurementicon.png",
    "https://vis.globe.gov/GLOBE/images/filter-icon-desel.png",
    "https://vis.globe.gov/GLOBE/images/filter-icon-white.png",
    "https://vis.globe.gov/GLOBE/images/globe-logo-title-desktop.jpg",
    "https://vis.globe.gov/GLOBE/images/green-check.png",
    "https://vis.globe.gov/GLOBE/images/info_icon.svg",
    "https://vis.globe.gov/GLOBE/images/large-globe-logo.png",
    "https://vis.globe.gov/GLOBE/images/left-chevron.png",
    "https://vis.globe.gov/GLOBE/images/legendbutton.png",
    "https://vis.globe.gov/GLOBE/images/link-icon.png",
    "https://vis.globe.gov/GLOBE/images/map-btn-blue.png",
    "https://vis.globe.gov/GLOBE/images/measurements-icon-sel.png",
    "https://vis.globe.gov/GLOBE/images/measurements-icon-unsel.png",
    "https://vis.globe.gov/GLOBE/images/mosquitogenera1_icon.png",
    "https://vis.globe.gov/GLOBE/images/mosquitogenera2_icon.png",
    "https://vis.globe.gov/GLOBE/images/mosquitogenera3_icon.png",
    "https://vis.globe.gov/GLOBE/images/mosquitogenera4_icon.png",
    "https://vis.globe.gov/GLOBE/images/mosquitogenera5_icon.png",
    "https://vis.globe.gov/GLOBE/images/mosquitogenera6_icon.png",
    "https://vis.globe.gov/GLOBE/images/mosquitogenera7_icon.png",
    "https://vis.globe.gov/GLOBE/images/mosquitohabitat1_icon.png",
    "https://vis.globe.gov/GLOBE/images/mosquitohabitat2_icon.png",
    "https://vis.globe.gov/GLOBE/images/mosquitohabitat3_icon.png",
    "https://vis.globe.gov/GLOBE/images/mosquitohabitat4_icon.png",
    "https://vis.globe.gov/GLOBE/images/multi-icon-desel.png",
    "https://vis.globe.gov/GLOBE/images/multi-icon-white.png",
    "https://vis.globe.gov/GLOBE/images/notsignin-icon-desel.png",
    "https://vis.globe.gov/GLOBE/images/notsignin-icon.png",
    "https://vis.globe.gov/GLOBE/images/plot-icon_on.png",
    "https://vis.globe.gov/GLOBE/images/protocol-icon-desel.png",
    "https://vis.globe.gov/GLOBE/images/protocol-icon-sel.png",
    "https://vis.globe.gov/GLOBE/images/protocol-icon-white.png",
    "https://vis.globe.gov/GLOBE/images/settings-icon-desel.png",
    "https://vis.globe.gov/GLOBE/images/settings-icon-white.png",
    "https://vis.globe.gov/GLOBE/images/signin-icon-white.png",
    "https://vis.globe.gov/GLOBE/images/soil_icon_10-size.png",
    "https://vis.globe.gov/GLOBE/images/soil_icon_14-size.png",
    "https://vis.globe.gov/GLOBE/images/soil_icon_18-size.png",
    "https://vis.globe.gov/GLOBE/images/soil_icon_22-size.png",
    "https://vis.globe.gov/GLOBE/images/soil_icon_26-size.png",
    "https://vis.globe.gov/GLOBE/images/table-ajax-loader.gif",
    "https://vis.globe.gov/GLOBE/images/table-icon_off.png",
    "https://vis.globe.gov/GLOBE/images/table-icon_on.png",
    "https://vis.globe.gov/GLOBE/images/vis-mobile-logo-sm.jpg",
    "https://vis.globe.gov/GLOBE/images/vis-mobile-logo.jpg",
    "https://vis.globe.gov/GLOBE/images/welcome-background.jpg",
    "https://vis.globe.gov/GLOBE/images/welcome-icon-sel.png",
    "https://vis.globe.gov/GLOBE/images/zoom_icon-on.png",
    "https://vis.globe.gov/GLOBE/javascript/ADATGUI.js",
    "https://vis.globe.gov/GLOBE/javascript/ADATmain.js",
    "https://vis.globe.gov/GLOBE/javascript/VISAnimation.js",
    "https://vis.globe.gov/GLOBE/javascript/VISGUI.js",
    "https://vis.globe.gov/GLOBE/javascript/VISmain.js",
    "https://vis.globe.gov/GLOBE/javascript/VISmanager.js",
    "https://vis.globe.gov/GLOBE/javascript/VISmap.js",
    "https://vis.globe.gov/GLOBE/javascript/autocomplete.js",
    "https://vis.globe.gov/GLOBE/javascript/bowser.min.js",
    "https://vis.globe.gov/GLOBE/javascript/common.js",
    "https://vis.globe.gov/GLOBE/javascript/dhtmlxWin.js",
    "https://vis.globe.gov/GLOBE/javascript/domain_config.js",
    "https://vis.globe.gov/GLOBE/javascript/jquery.deprecated.api.js",
    "https://vis.globe.gov/GLOBE/javascript/jquery.slimscroll.js",
    "https://vis.globe.gov/GLOBE/javascript/jquery.transit.min.js",
    "https://vis.globe.gov/GLOBE/javascript/jquery.ui.touch-punch.min.js",
    "https://vis.globe.gov/GLOBE/javascript/langpack/ADAT.welcome.en.html",
    "https://vis.globe.gov/GLOBE/javascript/listPopulator.js",
    "https://vis.globe.gov/GLOBE/javascript/multisitesplot.js",
    "https://vis.globe.gov/GLOBE/javascript/popupContents.js",
    "https://vis.globe.gov/GLOBE/javascript/popupContentsHelp.js",
    "https://vis.globe.gov/GLOBE/javascript/purify.min.js",
    "https://vis.globe.gov/GLOBE/javascript/savesearchfiltermain.js",
    "https://vis.globe.gov/GLOBE/javascript/slider.js",
    "https://vis.globe.gov/GLOBE/javascript/socialshare.js",
    "https://vis.globe.gov/GLOBELIB/dhtmlx/dhtmlx.css",
    "https://vis.globe.gov/GLOBELIB/dhtmlx/dhtmlx.js",
    "https://vis.globe.gov/GLOBELIB/jquery/jquery.autocomplete.css",
    "https://vis.globe.gov/GLOBELIB/jquery/jquery.autocomplete.js",
    "https://vis.globe.gov/GLOBELIB/jquery/jquery.balloon.min.js",
    "https://vis.globe.gov/GLOBELIB/openlayers/ol.css",
    "https://vis.globe.gov/GLOBELIB/openlayers/ol.js",
    "https://w.appzi.io/boot-wt-v2422-y41dgl.js",
    "https://w.appzi.io/w.js",
    "https://www.google-analytics.com/g/collect",
    "https://www.google.com/images/cleardot.gif",
    "https://www.googletagmanager.com/gtag/js",
    "https://www.googletagmanager.com/gtm.js",
    "https://www.gstatic.com/_/translate_http/_/ss/k=translate_http.tr.NJgGN_yGIWM.L.W.O/am=AAY/d=0/rs=AN8SPfrTSMIvWAFISYN4u74dPJrX0HgUsw/m=el_main_css",
    "https://www.gstatic.com/images/branding/product/2x/translate_24dp.png"
  ],
  "third_party_service_count": 18,
  "cookie_domains": [
    ".globe.gov",
    "datasearch.globe.gov"
  ],
  "viewport_meta_tag": true,
  "required_links_url": null,
  "required_links_text": null,
  "https_enforced": true,
  "hsts": true,
  "title": "GLOBE Advanced Data Access Tools",
  "description": null,
  "keywords": null,
  "og_title": null,
  "og_description": null,
  "og_article_published": null,
  "og_article_modified": null,
  "og_image": null,
  "og_type": null,
  "og_url": null,
  "canonical_link": null,
  "language": null,
  "language_link": "",
  "main_element_present": false,
  "robots_txt_detected": false,
  "robots_txt_url": "https://datasearch.globe.gov/robots.txt",
  "robots_txt_status_code": 404,
  "robots_txt_media_type": "text/html",
  "robots_txt_filesize": null,
  "robots_txt_crawl_delay": null,
  "robots_txt_sitemap_locations": null,
  "sitemap_xml_detected": false,
  "sitemap_xml_url": "https://datasearch.globe.gov/sitemap.xml",
  "sitemap_xml_status_code": 404,
  "sitemap_xml_media_type": "text/html",
  "sitemap_xml_filesize": null,
  "sitemap_xml_count": null,
  "sitemap_xml_lastmod": null,
  "sitemap_xml_pdf_count": null,
  "sitemap_xml_page_hash": null,
  "uswds_favicon": 0,
  "uswds_favicon_in_css": 0,
  "uswds_publicsans_font": 0,
  "uswds_inpage_css": 0,
  "uswds_usa_class_list": null,
  "uswds_banner_heres_how": false,
  "uswds_banner_heres_how-2": false,
  "uswds_usa_classes": 0,
  "uswds_string": 0,
  "uswds_string_in_css": 0,
  "uswds_semantic_version": null,
  "uswds_version": 0,
  "uswds_count": 0,
  "www_url": null,
  "www_status_code": null,
  "www_title": null
}