{
  "name": "gdd.hhs.gov",
  "initial_url": "https://gdd.hhs.gov",
  "initial_domain": "gdd.hhs.gov",
  "initial_base_domain": "hhs.gov",
  "initial_top_level_domain": "gov",
  "redirect": false,
  "url": "https://gdd.hhs.gov/",
  "domain": "gdd.hhs.gov",
  "base_domain": "hhs.gov",
  "top_level_domain": "gov",
  "live": true,
  "filter": false,
  "status_code": 200,
  "media_type": "text/html",
  "agency": "Department of Health and Human Services",
  "bureau": "Office of the Secretary",
  "branch": "Executive",
  "404_test": false,
  "source_list": [
    "final_url_websites"
  ],
  "public": null,
  "primary_scan_status": "completed",
  "accessibility_scan_status": "completed",
  "dns_scan_status": "completed",
  "not_found_scan_status": "completed",
  "performance_scan_status": "completed",
  "robots_txt_scan_status": "completed",
  "security_scan_status": "completed",
  "sitemap_xml_scan_status": "completed",
  "www_scan_status": "completed",
  "page_hash": "9856059d0ec7a38a0bd733a2b09bc7d2",
  "accessibility_violations": "{\"contrast\":9,\"images\":18,\"link-purpose\":33}",
  "pageviews": null,
  "visits": null,
  "ipv6": false,
  "hostname": "amazonaws.com",
  "cms": null,
  "login_provider": null,
  "login": null,
  "site_search": true,
  "search_dot_gov": null,
  "dap": false,
  "dap_parameters": "",
  "dap_version": "",
  "ga_tag_id": "G-8MHJMFBL7W",
  "third_party_service_domains": [
    "accounts.google.com",
    "apis.google.com",
    "buttons-config.sharethis.com",
    "cdn.onesignal.com",
    "connect.facebook.net",
    "content-youtube.googleapis.com",
    "content.googleapis.com",
    "ekr.zdassets.com",
    "fonts.googleapis.com",
    "fonts.gstatic.com",
    "graph.facebook.com",
    "img.youtube.com",
    "l.sharethis.com",
    "onesignal.com",
    "platform-api.sharethis.com",
    "riglynx.com",
    "riglynx.zendesk.com",
    "riglynxassets.s3.amazonaws.com",
    "s3-symbol-logo.tradingview.com",
    "s3.tradingview.com",
    "static.zdassets.com",
    "t.sharethis.com",
    "widget-sheriff.tradingview-widget.com",
    "www.googleapis.com",
    "www.googletagmanager.com",
    "www.gstatic.com",
    "www.tradingview-widget.com"
  ],
  "third_party_service_urls": [
    "https://accounts.google.com/_/IdpIFrameHttp/cspreport/fine-allowlist",
    "https://accounts.google.com/o/oauth2/iframerpc",
    "https://apis.google.com/_/scs/apps-static/_/js/k=oz.gapi.en_US.SnHyU412DY0.O/m=auth2",
    "client/rt=j/sv=1/d=1/ed=1/am=wQE/rs=AGLTcCObTkZu7kqIvAlB0bY4g3IzlKIb5g/cb=gapi.loaded_0",
    "https://apis.google.com/_/scs/apps-static/_/js/k=oz.gapi.en_US.SnHyU412DY0.O/m=googleapis_proxy/rt=j/sv=1/d=1/ed=1/am=wQE/rs=AGLTcCObTkZu7kqIvAlB0bY4g3IzlKIb5g/cb=gapi.loaded_0",
    "https://apis.google.com/js/googleapis.proxy.js",
    "https://buttons-config.sharethis.com/js/5eb0fc530ebc870012be74a8.js",
    "https://cdn.onesignal.com/sdks/OneSignalPageSDKES6.js",
    "https://connect.facebook.net/en_US/sdk.js",
    "https://content-youtube.googleapis.com/youtube/v3/liveBroadcasts",
    "https://content.googleapis.com/discovery/v1/apis/youtube/v3/rest",
    "https://ekr.zdassets.com/compose/bedc3afb-5ec6-4eb2-9f6f-cccd6ce91534",
    "https://fonts.googleapis.com/css",
    "https://fonts.gstatic.com/s/raleway/v34/1Pt_g8zYS_SKggPNyCgSQamb1W0lwk4S4WjNDrMfJh1Zyc61YA.woff",
    "https://fonts.gstatic.com/s/raleway/v34/1Ptug8zYS_SKggPNyC0IT4ttDfA.woff2",
    "https://graph.facebook.com/v4.0/riglynx/live_videos",
    "https://img.youtube.com/vi/-PYziyw_Jdc/hqdefault.jpg",
    "https://img.youtube.com/vi/2OpDmm0BUmY/hqdefault.jpg",
    "https://img.youtube.com/vi/9UTkPeVfmYo/hqdefault.jpg",
    "https://img.youtube.com/vi/IK1iBkvFJZo/hqdefault.jpg",
    "https://img.youtube.com/vi/OmPKGOwCLUs/hqdefault.jpg",
    "https://img.youtube.com/vi/_5wnN00eXew/hqdefault.jpg",
    "https://img.youtube.com/vi/_XQs5HW8lrY/hqdefault.jpg",
    "https://img.youtube.com/vi/aA87YNKhfus/hqdefault.jpg",
    "https://img.youtube.com/vi/cEpO-khnXbE/hqdefault.jpg",
    "https://img.youtube.com/vi/gXkI2cvnbrY/hqdefault.jpg",
    "https://img.youtube.com/vi/kqh1RnYYIN0/hqdefault.jpg",
    "https://img.youtube.com/vi/lhzsOT5sBjg/hqdefault.jpg",
    "https://img.youtube.com/vi/nNZG_iwVLYs/hqdefault.jpg",
    "https://img.youtube.com/vi/r63K-SL6z44/hqdefault.jpg",
    "https://img.youtube.com/vi/xJfMQ7Lqeus/hqdefault.jpg",
    "https://l.sharethis.com/pview",
    "https://l.sharethis.com/sc",
    "https://onesignal.com/api/v1/sync/5acbc925-d6cd-450c-a2cd-fcb19e6a8a6a/web",
    "https://platform-api.sharethis.com/js/sharethis.js",
    "https://riglynx.com/public/css/all.min.css",
    "https://riglynx.com/public/css/bootstrap.min.css",
    "https://riglynx.com/public/css/bxslider.min.css",
    "https://riglynx.com/public/css/demo.min.css",
    "https://riglynx.com/public/css/fancybox.min.css",
    "https://riglynx.com/public/css/main.css",
    "https://riglynx.com/public/css/owl.min.css",
    "https://riglynx.com/public/css/pomelo-toast.min.css",
    "https://riglynx.com/public/fonts/Raleway-Regular.ttf",
    "https://riglynx.com/public/images/cube-loader.gif",
    "https://riglynx.com/public/images/fb.png",
    "https://riglynx.com/public/images/logo-1.png",
    "https://riglynx.com/public/images/logo.png",
    "https://riglynx.com/public/images/tikic.png",
    "https://riglynx.com/public/images/tiktok.png",
    "https://riglynx.com/public/images/user-icon.png",
    "https://riglynx.com/public/images/youtube.png",
    "https://riglynx.com/public/images/youtube_live_offline.png",
    "https://riglynx.com/public/js/OneSignalSDK.min.js",
    "https://riglynx.com/public/js/advert-function.min.js",
    "https://riglynx.com/public/js/all.min.js",
    "https://riglynx.com/public/js/bootstrap.min.js",
    "https://riglynx.com/public/js/bxslider.min.js",
    "https://riglynx.com/public/js/chat/searchtextvalue.js",
    "https://riglynx.com/public/js/fontawesome.min.js",
    "https://riglynx.com/public/js/googleapi.min.js",
    "https://riglynx.com/public/js/googleplatform.min.js",
    "https://riglynx.com/public/js/jQuery.min.js",
    "https://riglynx.com/public/js/jquery.cookie.min.js",
    "https://riglynx.com/public/js/jquery.desoslide.min.js",
    "https://riglynx.com/public/js/lightslider.min.js",
    "https://riglynx.com/public/js/main.min.js",
    "https://riglynx.com/public/js/owl.min.js",
    "https://riglynx.com/public/js/pomelo-toast.min.js",
    "https://riglynx.com/public/js/popper.min.js",
    "https://riglynx.com/public/webfonts/fa-brands-400.woff2",
    "https://riglynx.com/public/webfonts/fa-regular-400.woff2",
    "https://riglynx.com/public/webfonts/fa-solid-900.woff2",
    "https://riglynx.zendesk.com/embeddable/config",
    "https://riglynxassets.s3.amazonaws.com/uploads/NewsLetterConfig/bannnerImage.png",
    "https://riglynxassets.s3.amazonaws.com/uploads/blog_images/1d2b566f5aaea6f02538ba2622a56135.png",
    "https://riglynxassets.s3.amazonaws.com/uploads/blog_images/1d5c720120d652c2a8cfaeb1379349dc.jpeg",
    "https://riglynxassets.s3.amazonaws.com/uploads/blog_images/2777ffcc96239575302539c9aa0dda51.PNG",
    "https://riglynxassets.s3.amazonaws.com/uploads/blog_images/2cd9208c49d7342e8bfb8f9ff4971ba6.png",
    "https://riglynxassets.s3.amazonaws.com/uploads/blog_images/4171b3835f96c7df97e962c66f18ad7f.png",
    "https://riglynxassets.s3.amazonaws.com/uploads/blog_images/47a1e9390dfdc91ddfb7491942579de2.png",
    "https://riglynxassets.s3.amazonaws.com/uploads/blog_images/4b02b648117c1039eb545b0f1ce9dbe7.jpg",
    "https://riglynxassets.s3.amazonaws.com/uploads/blog_images/56093f6fb379eb1cfe12cdfe49da9d94.jpeg",
    "https://riglynxassets.s3.amazonaws.com/uploads/blog_images/5b46a3a7bbea0c2873d8a422c2ff76fe.jpeg",
    "https://riglynxassets.s3.amazonaws.com/uploads/blog_images/6a5d8dd09d5d0fa86583330eaff7f01a.jpg",
    "https://riglynxassets.s3.amazonaws.com/uploads/blog_images/7211e328ae8df0fa381b8bcdff7c2f72.jpg",
    "https://riglynxassets.s3.amazonaws.com/uploads/blog_images/72b35ff24001190bd77bee8c6dd58f25.png",
    "https://riglynxassets.s3.amazonaws.com/uploads/blog_images/7c51285e50b390144ee56377bcda5965.png",
    "https://riglynxassets.s3.amazonaws.com/uploads/blog_images/83d06f72507edcd3e101fea987f32965.png",
    "https://riglynxassets.s3.amazonaws.com/uploads/blog_images/93cd6339ef760edf5804fdcf8b1b8ccf.jpg",
    "https://riglynxassets.s3.amazonaws.com/uploads/blog_images/9bd4c406641f7e8977e9dd5c36f44b5d.jpeg",
    "https://riglynxassets.s3.amazonaws.com/uploads/blog_images/a75222f44072c03266a06796e21bc443.png",
    "https://riglynxassets.s3.amazonaws.com/uploads/blog_images/a8ed81dbe2542a1f1aa2b26f764f0862.jpeg",
    "https://riglynxassets.s3.amazonaws.com/uploads/blog_images/b2b95ff9de29574f0e6b55dd0a8ad398.jpg",
    "https://riglynxassets.s3.amazonaws.com/uploads/blog_images/bc6a0d6c2b82fd14fae7e7e9fc730850.png",
    "https://riglynxassets.s3.amazonaws.com/uploads/blog_images/c3786c40bc7e331f8a7da2b66112f4f0.jpeg",
    "https://riglynxassets.s3.amazonaws.com/uploads/blog_images/c71b4d2319cace8d7d8f29b81197ca9b.png",
    "https://riglynxassets.s3.amazonaws.com/uploads/blog_images/e24a5f3f39422a148fffffc08ee36ce4.png",
    "https://riglynxassets.s3.amazonaws.com/uploads/blog_images/e868535c7b31d32470d81d12df50ab44.png",
    "https://riglynxassets.s3.amazonaws.com/uploads/blog_images/e9e2a0b393448dd5fc67f67c767c3cea.png",
    "https://riglynxassets.s3.amazonaws.com/uploads/blog_images/ededdbbbf1b52324a117bb7d519e1cff.jpg",
    "https://riglynxassets.s3.amazonaws.com/uploads/blog_images/f09f0a0e0b5e0034a97e5bdd2c167c84.png",
    "https://riglynxassets.s3.amazonaws.com/uploads/blog_images/f6c584714fe2de96d083a51e1c53c0a8.png",
    "https://riglynxassets.s3.amazonaws.com/uploads/blog_images/f7a9c1516894fbdf0d1c47a14310e01d.jpg",
    "https://riglynxassets.s3.amazonaws.com/uploads/events/42bbed5c019b3213c6e2dab250facdaa.png",
    "https://riglynxassets.s3.amazonaws.com/uploads/events/8847755c2abc5a1451b1ad2e8921659a.png",
    "https://riglynxassets.s3.amazonaws.com/uploads/events/a7fc714cef1cef73023e91505dba9fc3.png",
    "https://riglynxassets.s3.amazonaws.com/uploads/sponsers/0a8597a8ecff434da3485c26acbe9ae9.png",
    "https://riglynxassets.s3.amazonaws.com/uploads/sponsers/18be760306566b75560eaf4a2a824804.png",
    "https://riglynxassets.s3.amazonaws.com/uploads/sponsers/19f9fc1df8cf0fabcf0ccb9bcff14846.png",
    "https://riglynxassets.s3.amazonaws.com/uploads/sponsers/1df73aa18881730b4d47b11340754212.png",
    "https://riglynxassets.s3.amazonaws.com/uploads/sponsers/24bebcadba2fca97f186fa72d8f8bb74.png",
    "https://riglynxassets.s3.amazonaws.com/uploads/sponsers/45ca97556f07e8516061dccd63854e66.png",
    "https://riglynxassets.s3.amazonaws.com/uploads/sponsers/4add1257354f110c92c03fe1bd3653c5.png",
    "https://riglynxassets.s3.amazonaws.com/uploads/sponsers/81ce1a43f6769bfe023ceef0289b21cc.png",
    "https://riglynxassets.s3.amazonaws.com/uploads/sponsers/96a3a16460b480f3850d730eac526edb.png",
    "https://riglynxassets.s3.amazonaws.com/uploads/sponsers/9cb3306476b744f3e420603dea7bd419.jpg",
    "https://riglynxassets.s3.amazonaws.com/uploads/sponsers/c5af9b779c725d17ae9a18f831195bf5.png",
    "https://riglynxassets.s3.amazonaws.com/uploads/sponsers/d43b9f71abb2e334dc6a9c25ef6a32d9.png",
    "https://riglynxassets.s3.amazonaws.com/uploads/sponsers/d99b03504d39b37ab961737bc5329df8.jpg",
    "https://riglynxassets.s3.amazonaws.com/uploads/sponsers/db83964f26f4891cde02f35b6210ff8e.png",
    "https://riglynxassets.s3.amazonaws.com/uploads/sponsers/e5fa4ba00aeefbdf170a2294f118f966.png",
    "https://riglynxassets.s3.amazonaws.com/uploads/sponsers/f32ebc44f5c6a2e77cfce1ead60b476a.png",
    "https://riglynxassets.s3.amazonaws.com/uploads/sponsers/f507b3cf8e9d6f2cdbdb689c924db565.png",
    "https://s3-symbol-logo.tradingview.com/crude-oil.svg",
    "https://s3-symbol-logo.tradingview.com/natural-gas.svg",
    "https://s3.tradingview.com/external-embedding/embed-widget-ticker-tape.js",
    "https://static.zdassets.com/ekr/snippet.js",
    "https://static.zdassets.com/web_widget/classic/latest/fda6cd35495c75f83508d9d2e77ee33d.mp3",
    "https://static.zdassets.com/web_widget/classic/latest/web-widget-chat-incoming-message-notification-5016640.js",
    "https://static.zdassets.com/web_widget/classic/latest/web-widget-chat-sdk-5016640.js",
    "https://static.zdassets.com/web_widget/classic/latest/web-widget-locales/classic/en-us-json-5016640.js",
    "https://static.zdassets.com/web_widget/classic/latest/web-widget-main-5016640.js",
    "https://t.sharethis.com/1/k/t.dhj",
    "https://t.sharethis.com/d/a.gif",
    "https://widget-sheriff.tradingview-widget.com/sheriff/api/v1/rules/search",
    "https://www.googleapis.com/oauth2/v4/token",
    "https://www.googletagmanager.com/gtag/js",
    "https://www.gstatic.com/_/mss/boq-identity/_/js/k=boq-identity.IdpIFrameHttp.en_US.90QocFlViRY.es5.O/am=AAY/d=1/rs=AOaEmlEhirtSBUS4Q37kRtjtWwhoIgHx_Q/m=base",
    "https://www.tradingview-widget.com/static/bundles/embed/1057.f56daf950e75ccaf89ab.js",
    "https://www.tradingview-widget.com/static/bundles/embed/15870.c1b29293fd5c30d16076.js",
    "https://www.tradingview-widget.com/static/bundles/embed/30649.abe93f045487b8800b5b.js",
    "https://www.tradingview-widget.com/static/bundles/embed/3579.d4ce023e54009adf69b3.css",
    "https://www.tradingview-widget.com/static/bundles/embed/38752.e464d157e791b8dd3734.css",
    "https://www.tradingview-widget.com/static/bundles/embed/44883.585fac974704d1d85ab0.css",
    "https://www.tradingview-widget.com/static/bundles/embed/45953.cb2c653b8471ebe8a0fb.js",
    "https://www.tradingview-widget.com/static/bundles/embed/47597.c4b45b19cf11d15735f0.css",
    "https://www.tradingview-widget.com/static/bundles/embed/53014.b7653edec5b9a6b44346.js",
    "https://www.tradingview-widget.com/static/bundles/embed/55822.9a6921d85f208ac207e1.css",
    "https://www.tradingview-widget.com/static/bundles/embed/61997.9b223907748904842eec.js",
    "https://www.tradingview-widget.com/static/bundles/embed/63985.621169e8f49b1cabac32.js",
    "https://www.tradingview-widget.com/static/bundles/embed/64828.35532bec9edbf525f4d8.css",
    "https://www.tradingview-widget.com/static/bundles/embed/69022.29eac48411485b105947.js",
    "https://www.tradingview-widget.com/static/bundles/embed/70452.d9ceafc180bfdcf9694d.js",
    "https://www.tradingview-widget.com/static/bundles/embed/74269.4c2ffd57fc6f3a9479c0.js",
    "https://www.tradingview-widget.com/static/bundles/embed/80259.7ffdb5fd1aae95c1b34f.css",
    "https://www.tradingview-widget.com/static/bundles/embed/83439.8716e2cfa1fe6f4ee07b.css",
    "https://www.tradingview-widget.com/static/bundles/embed/94562.8341c735a59d13cb56c7.css",
    "https://www.tradingview-widget.com/static/bundles/embed/98681.545aa1b123cab8d6dbef.css",
    "https://www.tradingview-widget.com/static/bundles/embed/99812.58ae29b7c4151323f209.js",
    "https://www.tradingview-widget.com/static/bundles/embed/embed_ticker_tape_widget.fc9da5352c3142c33221.js",
    "https://www.tradingview-widget.com/static/bundles/embed/en.56316.4f17b20714d98c029320.js",
    "https://www.tradingview-widget.com/static/bundles/embed/en.56977.d37d202c35abfed7ea22.js",
    "https://www.tradingview-widget.com/static/bundles/embed/runtime-embed_ticker_tape_widget.221c73249eff38953343.js",
    "https://www.tradingview-widget.com/static/bundles/embed/tradingview-copyright-data-impl.98b6cc4d3e97dee809ed.js"
  ],
  "third_party_service_count": 27,
  "cookie_domains": [
    ".gdd.hhs.gov",
    ".hhs.gov",
    "gdd.hhs.gov"
  ],
  "viewport_meta_tag": true,
  "required_links_url": [
    "about",
    "privacy"
  ],
  "required_links_text": [
    "privacy policy"
  ],
  "https_enforced": false,
  "hsts": true,
  "title": "Rig Lynx - Home",
  "description": "",
  "keywords": "oil and gas jobs, job search, career, employment, oil and gas news, oil and gas engineering and sciences, oilfield services, sales, trades, oil and gas events",
  "og_title": "Rig Lynx - Home",
  "og_description": "",
  "og_article_published": null,
  "og_article_modified": null,
  "og_image": "",
  "og_type": "article",
  "og_url": "",
  "canonical_link": null,
  "language": "en-US",
  "language_link": "",
  "main_element_present": false,
  "robots_txt_detected": true,
  "robots_txt_url": "https://gdd.hhs.gov/robots.txt",
  "robots_txt_status_code": 200,
  "robots_txt_media_type": "text/html",
  "robots_txt_filesize": 0,
  "robots_txt_crawl_delay": null,
  "robots_txt_sitemap_locations": null,
  "sitemap_xml_detected": true,
  "sitemap_xml_url": "https://gdd.hhs.gov/sitemap.xml",
  "sitemap_xml_status_code": 200,
  "sitemap_xml_media_type": "text/html",
  "sitemap_xml_filesize": 0,
  "sitemap_xml_count": 0,
  "sitemap_xml_lastmod": null,
  "sitemap_xml_pdf_count": 0,
  "sitemap_xml_page_hash": "1c210c89a8d9088362b442d3253c1686",
  "uswds_favicon": 0,
  "uswds_favicon_in_css": 0,
  "uswds_publicsans_font": 0,
  "uswds_inpage_css": 0,
  "uswds_usa_class_list": null,
  "uswds_banner_heres_how": false,
  "uswds_usa_classes": 0,
  "uswds_string": 0,
  "uswds_string_in_css": 0,
  "uswds_semantic_version": null,
  "uswds_version": 0,
  "uswds_count": 0,
  "www_url": "https://www.gdd.hhs.gov",
  "www_status_code": 200,
  "www_title": "Rig Lynx - Home"
}