{
  "name": "login.microsoftonline.com",
  "initial_url": "https://knowman.nlm.nih.gov",
  "initial_domain": "knowman.nlm.nih.gov",
  "initial_base_domain": "nih.gov",
  "initial_top_level_domain": "gov",
  "redirect": true,
  "url": "https://login.microsoftonline.com/14b77578-9773-42d5-8507-251ca2dc2b06/oauth2/authorize?client%5Fid=00000003%2D0000%2D0ff1%2Dce00%2D000000000000&response%5Fmode=form%5Fpost&response%5Ftype=code%20id%5Ftoken&resource=00000003%2D0000%2D0ff1%2Dce00%2D000000000000&scope=openid&nonce=8CC97FA06A6FB28FD3626B70C5199A6ADD8C96712868A63C%2D371C7060E0BEF3103CB3C4D2FF70C3B58061A6655A9C2F88D22122C40F24D6DE&redirect%5Furi=https%3A%2F%2Fnih%2Esharepoint%2Ecom%2F%5Fforms%2Fdefault%2Easpx&state=OD0w&claims=%7B%22id%5Ftoken%22%3A%7B%22xms%5Fcc%22%3A%7B%22values%22%3A%5B%22CP1%22%5D%7D%7D%7D&wsucxt=1&cobrandid=11bd8083%2D87e0%2D41b5%2Dbb78%2D0bc43c8a8e8a&client%2Drequest%2Did=b8fe83a1%2D80e7%2D8000%2D34a6%2D8864b93e91e3",
  "domain": "login.microsoftonline.com",
  "base_domain": "microsoftonline.com",
  "top_level_domain": "com",
  "live": true,
  "filter": false,
  "status_code": 200,
  "media_type": "text/html",
  "agency": "Department of Health and Human Services",
  "bureau": "National Institutes of Health",
  "branch": "Executive",
  "404_test": false,
  "source_list": [
    "pulse",
    "cisa"
  ],
  "public": null,
  "primary_scan_status": "completed",
  "accessibility_scan_status": "execution_context_destroyed",
  "dns_scan_status": "completed",
  "not_found_scan_status": "completed",
  "performance_scan_status": "completed",
  "robots_txt_scan_status": "completed",
  "security_scan_status": "unknown_error",
  "sitemap_xml_scan_status": "completed",
  "www_scan_status": "dns_resolution_error",
  "page_hash": "b42a15ea2fb3b526c68a78108fecf993",
  "accessibility_violations": null,
  "ipv6": true,
  "hostname": null,
  "cms": null,
  "login_provider": null,
  "login": null,
  "site_search": false,
  "search_dot_gov": null,
  "dap": false,
  "dap_parameters": "",
  "dap_version": "",
  "ga_tag_id": "",
  "third_party_service_domains": [
    "aadcdn.msftauth.net",
    "aadcdn.msftauthimages.net",
    "login.live.com"
  ],
  "third_party_service_urls": [
    "https://aadcdn.msftauth.net/ests/2.1/content/cdnbundles/converged.v2.login.min_81imvbluez-v5hbzpkxfcg2.css",
    "https://aadcdn.msftauth.net/ests/2.1/content/cdnbundles/ux.converged.login.strings-en.min_58kdvbzctdjk48yetaekng2.js",
    "https://aadcdn.msftauth.net/shared/1.0/content/images/signin-options_3e3f6b73c3f310c31d2c4d131a8ab8c6.svg",
    "https://aadcdn.msftauth.net/shared/1.0/content/js/ConvergedLogin_PCore_iO_VLhbr8gXvmCnvbzDI7A2.js",
    "https://aadcdn.msftauth.net/shared/1.0/content/js/asyncchunk/convergedlogin_pcustomizationloader_72a1051aa2aa2943d8c1.js",
    "https://aadcdn.msftauth.net/shared/1.0/content/js/asyncchunk/convergedlogin_pstringcustomizationhelper_c4928fb5cff147a39780.js",
    "https://aadcdn.msftauth.net/shared/1.0/content/js/oneDs_f2e0f4a029670f10d892.js",
    "https://aadcdn.msftauthimages.net/dbd5a2dd-f48yuzqkouwlbp11ejs1hwyfcpjfqxigh07epo4men0/logintenantbranding/0/bannerlogo",
    "https://aadcdn.msftauthimages.net/dbd5a2dd-f48yuzqkouwlbp11ejs1hwyfcpjfqxigh07epo4men0/logintenantbranding/0/illustration",
    "https://login.live.com/Me.htm"
  ],
  "third_party_service_count": 3,
  "cookie_domains": [
    ".login.microsoftonline.com",
    "login.microsoftonline.com"
  ],
  "viewport_meta_tag": true,
  "required_links_url": [
    "privacy"
  ],
  "required_links_text": null,
  "https_enforced": null,
  "hsts": null,
  "title": "Sign in to your account",
  "description": null,
  "keywords": null,
  "og_title": null,
  "og_description": null,
  "og_article_published": null,
  "og_article_modified": null,
  "og_image": null,
  "og_type": null,
  "og_url": null,
  "canonical_link": null,
  "language": "en",
  "language_link": "",
  "main_element_present": false,
  "robots_txt_detected": false,
  "robots_txt_url": "https://login.microsoftonline.com/14b77578-9773-42d5-8507-251ca2dc2b06/oauth2/authorize?client%5Fid=00000003%2D0000%2D0ff1%2Dce00%2D000000000000&response%5Fmode=form%5Fpost&response%5Ftype=code%20id%5Ftoken&resource=00000003%2D0000%2D0ff1%2Dce00%2D000000000000&scope=openid&nonce=27DC9D82C2E3D207FD1BB7CA6BDFCE908CB82BD2F6DC7EBC%2D2374035A61DE1D30A59DC63F9BAE3C78A9D48C3085DA19618BB59488F0652A69&redirect%5Furi=https%3A%2F%2Fnih%2Esharepoint%2Ecom%2F%5Fforms%2Fdefault%2Easpx&state=OD0w&claims=%7B%22id%5Ftoken%22%3A%7B%22xms%5Fcc%22%3A%7B%22values%22%3A%5B%22CP1%22%5D%7D%7D%7D&wsucxt=1&cobrandid=11bd8083%2D87e0%2D41b5%2Dbb78%2D0bc43c8a8e8a&client%2Drequest%2Did=b9fe83a1%2Df044%2D8000%2D1a7a%2Dfae3169b9166",
  "robots_txt_status_code": 200,
  "robots_txt_media_type": "text/html",
  "robots_txt_filesize": null,
  "robots_txt_crawl_delay": null,
  "robots_txt_sitemap_locations": null,
  "sitemap_xml_detected": false,
  "sitemap_xml_url": "https://login.microsoftonline.com/14b77578-9773-42d5-8507-251ca2dc2b06/oauth2/authorize?client%5Fid=00000003%2D0000%2D0ff1%2Dce00%2D000000000000&response%5Fmode=form%5Fpost&response%5Ftype=code%20id%5Ftoken&resource=00000003%2D0000%2D0ff1%2Dce00%2D000000000000&scope=openid&nonce=9385D25403F326ABDAFB3CB3CB0DD59874457F404722EA4F%2D6EEFEE16E5AB1A33A3047C053C34296E0F39F594ED260B5E244A8D68D6A892E8&redirect%5Furi=https%3A%2F%2Fnih%2Esharepoint%2Ecom%2F%5Fforms%2Fdefault%2Easpx&state=OD0w&claims=%7B%22id%5Ftoken%22%3A%7B%22xms%5Fcc%22%3A%7B%22values%22%3A%5B%22CP1%22%5D%7D%7D%7D&wsucxt=1&cobrandid=11bd8083%2D87e0%2D41b5%2Dbb78%2D0bc43c8a8e8a&client%2Drequest%2Did=b9fe83a1%2Df09f%2D8000%2D34a6%2D8d67f6c237d6",
  "sitemap_xml_status_code": 200,
  "sitemap_xml_media_type": "text/html",
  "sitemap_xml_filesize": null,
  "sitemap_xml_count": null,
  "sitemap_xml_lastmod": null,
  "sitemap_xml_pdf_count": null,
  "sitemap_xml_page_hash": null,
  "uswds_favicon": 0,
  "uswds_favicon_in_css": 0,
  "uswds_publicsans_font": 0,
  "uswds_inpage_css": 0,
  "uswds_usa_class_list": null,
  "uswds_banner_heres_how": false,
  "uswds_usa_classes": 0,
  "uswds_string": 0,
  "uswds_string_in_css": 0,
  "uswds_semantic_version": null,
  "uswds_version": 0,
  "uswds_count": 0,
  "www_url": null,
  "www_status_code": null,
  "www_title": null
}