{
  "name": "radar.weather.gov",
  "initial_url": "https://radar.weather.gov",
  "initial_domain": "radar.weather.gov",
  "initial_base_domain": "weather.gov",
  "initial_top_level_domain": "gov",
  "redirect": false,
  "url": "https://radar.weather.gov/",
  "domain": "radar.weather.gov",
  "base_domain": "weather.gov",
  "top_level_domain": "gov",
  "live": true,
  "filter": false,
  "status_code": 200,
  "media_type": "unknown",
  "agency": "Department of Commerce",
  "bureau": "National Oceanic and Atmospheric Administration",
  "branch": "Executive",
  "404_test": true,
  "source_list": [
    "dap",
    "pulse",
    "omb_idea",
    "2020_eot"
  ],
  "public": true,
  "scan_date": "2025-02-08T15:24:04.433Z",
  "primary_scan_status": "completed",
  "accessibility_scan_status": "completed",
  "dns_scan_status": "completed",
  "not_found_scan_status": "completed",
  "performance_scan_status": "completed",
  "robots_txt_scan_status": "completed",
  "security_scan_status": "completed",
  "sitemap_xml_scan_status": "completed",
  "accessibility_violations": "{\"language\":1}",
  "ipv6": true,
  "hostname": "edgekey.net",
  "cms": null,
  "login_provider": null,
  "login": null,
  "site_search": true,
  "search_dot_gov": null,
  "dap": true,
  "dap_parameters": {
    "agency": "DOC",
    "subagency": "NOAA"
  },
  "dap_version": "20241218 v8.5 - GA4",
  "ga_tag_id": "G-CSLL4ZEK4L,G-9289EXGSWQ",
  "third_party_service_domains": [
    "basemaps-api.arcgis.com",
    "cdn.arcgis.com",
    "cdn.jsdelivr.net",
    "dap.digitalgov.gov",
    "opengeo.ncep.noaa.gov",
    "www.google-analytics.com",
    "www.googletagmanager.com"
  ],
  "third_party_service_urls": [
    "https://basemaps-api.arcgis.com/arcgis/rest/services/World_Basemap_v2/VectorTileServer/tile/3/2/1.pbf",
    "https://basemaps-api.arcgis.com/arcgis/rest/services/World_Basemap_v2/VectorTileServer/tile/3/2/2.pbf",
    "https://basemaps-api.arcgis.com/arcgis/rest/services/World_Basemap_v2/VectorTileServer/tile/3/3/1.pbf",
    "https://basemaps-api.arcgis.com/arcgis/rest/services/World_Basemap_v2/VectorTileServer/tile/3/3/2.pbf",
    "https://basemaps-api.arcgis.com/arcgis/rest/services/styles/ArcGIS:Streets",
    "https://cdn.arcgis.com/sharing/rest/content/items/de26a3cf4cc9451298ea173c4b324736/resources/sprites/sprite.json",
    "https://cdn.arcgis.com/sharing/rest/content/items/de26a3cf4cc9451298ea173c4b324736/resources/sprites/sprite.png",
    "https://cdn.jsdelivr.net/npm/@fontsource/arial/400-italic.css",
    "https://cdn.jsdelivr.net/npm/@fontsource/arial/400.css",
    "https://cdn.jsdelivr.net/npm/@fontsource/arial/700.css",
    "https://dap.digitalgov.gov/Universal-Federated-Analytics-Min.js",
    "https://dap.digitalgov.gov/web-vitals/dist/web-vitals.attribution.iife.js",
    "https://opengeo.ncep.noaa.gov/geoserver/alaska/alaska_bref_qcd/ows",
    "https://opengeo.ncep.noaa.gov/geoserver/carib/carib_bref_qcd/ows",
    "https://opengeo.ncep.noaa.gov/geoserver/conus/conus_bref_qcd/ows",
    "https://opengeo.ncep.noaa.gov/geoserver/guam/guam_bref_qcd/ows",
    "https://opengeo.ncep.noaa.gov/geoserver/hawaii/hawaii_bref_qcd/ows",
    "https://www.google-analytics.com/g/collect",
    "https://www.googletagmanager.com/gtag/js"
  ],
  "third_party_service_count": 7,
  "cookie_domains": [
    ".weather.gov"
  ],
  "viewport_meta_tag": true,
  "cumulative_layout_shift": "0.003101396891276042",
  "largest_contentful_paint": "174.30000001192093",
  "required_links_url": [
    "about",
    "foia",
    "privacy"
  ],
  "required_links_text": [
    "foia",
    "freedom of information act",
    "privacy policy"
  ],
  "https_enforced": true,
  "hsts": true,
  "title": "NWS Radar",
  "description": null,
  "keywords": null,
  "og_title": null,
  "og_description": null,
  "og_article_published": null,
  "og_article_modified": null,
  "og_image": null,
  "og_type": null,
  "og_url": null,
  "canonical_link": null,
  "language": null,
  "language_link": "",
  "main_element_present": true,
  "robots_txt_detected": false,
  "robots_txt_url": "https://radar.weather.gov/robots.txt",
  "robots_txt_status_code": 404,
  "robots_txt_media_type": "text/html",
  "robots_txt_filesize": null,
  "robots_txt_crawl_delay": null,
  "robots_txt_sitemap_locations": null,
  "sitemap_xml_detected": false,
  "sitemap_xml_url": "https://radar.weather.gov/sitemap.xml",
  "sitemap_xml_status_code": 404,
  "sitemap_xml_media_type": "text/html",
  "sitemap_xml_filesize": null,
  "sitemap_xml_count": null,
  "sitemap_xml_pdf_count": null,
  "uswds_favicon": 0,
  "uswds_favicon_in_css": 0,
  "uswds_publicsans_font": 0,
  "uswds_inpage_css": 0,
  "uswds_usa_class_list": null,
  "uswds_banner_heres_how": false,
  "uswds_usa_classes": 0,
  "uswds_string": 0,
  "uswds_string_in_css": 0,
  "uswds_semantic_version": null,
  "uswds_version": 0,
  "uswds_count": 0,
  "www_scan_status": "dns_resolution_error",
  "www_url": null,
  "www_status_code": null,
  "www_title": null
}