{
  "name": "swalwell.house.gov",
  "initial_url": "https://swalwell.house.gov",
  "initial_domain": "swalwell.house.gov",
  "initial_base_domain": "house.gov",
  "initial_top_level_domain": "gov",
  "redirect": false,
  "url": "https://swalwell.house.gov/",
  "domain": "swalwell.house.gov",
  "base_domain": "house.gov",
  "top_level_domain": "gov",
  "live": true,
  "filter": false,
  "status_code": 200,
  "media_type": "text/html",
  "agency": "The Legislative Branch",
  "bureau": "US House of Representatives",
  "branch": "Legislative",
  "404_test": true,
  "source_list": [
    "2020_eot"
  ],
  "public": null,
  "scan_date": "2025-02-07T05:39:06.793Z",
  "primary_scan_status": "completed",
  "accessibility_scan_status": "completed",
  "dns_scan_status": "completed",
  "not_found_scan_status": "completed",
  "performance_scan_status": "completed",
  "robots_txt_scan_status": "completed",
  "security_scan_status": "completed",
  "sitemap_xml_scan_status": "completed",
  "accessibility_violations": "{\"contrast\":10}",
  "ipv6": true,
  "hostname": "akamaitechnologies.com",
  "cms": "Drupal",
  "login_provider": null,
  "login": null,
  "site_search": true,
  "search_dot_gov": null,
  "dap": false,
  "dap_parameters": "",
  "dap_version": "",
  "ga_tag_id": "G-2RYWTQGJ71",
  "third_party_service_domains": [
    "api.hcaptcha.com",
    "cdnjs.cloudflare.com",
    "connect.facebook.net",
    "fonts.googleapis.com",
    "fonts.gstatic.com",
    "hcaptcha.com",
    "maxst.icons8.com",
    "newassets.hcaptcha.com",
    "platform.twitter.com",
    "scontent-sea1-1.xx.fbcdn.net",
    "static.xx.fbcdn.net",
    "syndication.twitter.com",
    "www.facebook.com",
    "www.googletagmanager.com",
    "www.instagram.com"
  ],
  "third_party_service_urls": [
    "https://api.hcaptcha.com/checksiteconfig",
    "https://cdnjs.cloudflare.com/ajax/libs/animate.css/4.1.1/animate.min.css",
    "https://connect.facebook.net/en_US/sdk.js",
    "https://fonts.googleapis.com/css",
    "https://fonts.gstatic.com/s/oswald/v53/TK3_WkUHHAIjg75cFRf3bXL8LICs1_FvsUZiYySUhiCXAA.woff",
    "https://hcaptcha.com/1/api.js",
    "https://maxst.icons8.com/vue-static/landings/line-awesome/line-awesome/1.3.0/css/line-awesome.min.css",
    "https://maxst.icons8.com/vue-static/landings/line-awesome/line-awesome/1.3.0/fonts/la-solid-900.woff2",
    "https://newassets.hcaptcha.com/c/7e1303d8c1ca17eba040bd283c0bd341b743be0c7a2fc77956839e6191feb9e6/hsw.js",
    "https://platform.twitter.com/js/timeline.e108540dddc96e4b707f5cf259a582d7.js",
    "https://platform.twitter.com/widgets.js",
    "https://scontent-sea1-1.xx.fbcdn.net/v/t39.30808-1/324093254_1301645247352826_6305374521238836709_n.jpg",
    "https://scontent-sea1-1.xx.fbcdn.net/v/t39.30808-6/323435324_698880818552316_2199691820513908206_n.jpg",
    "https://static.xx.fbcdn.net/rsrc.php/v4/yB/r/0bWEtGbW7yi.js",
    "https://static.xx.fbcdn.net/rsrc.php/v4/yF/r/p55HfXW__mM.js",
    "https://static.xx.fbcdn.net/rsrc.php/v4/yH/r/ieeHDjcGsIR.js",
    "https://static.xx.fbcdn.net/rsrc.php/v4/yH/r/xgVgalBG80z.png",
    "https://static.xx.fbcdn.net/rsrc.php/v4/yT/r/VuRstRCPjmu.png",
    "https://static.xx.fbcdn.net/rsrc.php/v4/yV/r/7qUMqLqVHNu.js",
    "https://static.xx.fbcdn.net/rsrc.php/v4/yY/r/GPfU2goEGev.js",
    "https://static.xx.fbcdn.net/rsrc.php/v4/yw/r/tt7UDeyVUba.png",
    "https://static.xx.fbcdn.net/rsrc.php/v4/yx/r/eK0bnzmYG5g.js",
    "https://static.xx.fbcdn.net/rsrc.php/v4iEBX4/ya/l/en_US/Yi1EwSfun-P.js",
    "https://static.xx.fbcdn.net/rsrc.php/v4iEpO4/yJ/l/en_US/nAYPeoAfUtY.js",
    "https://static.xx.fbcdn.net/rsrc.php/v4iLl54/y7/l/en_US/nJ1XUz8j1Ol.js",
    "https://static.xx.fbcdn.net/rsrc.php/v5/y4/l/0",
    "cross/i8lzpO3BnNo.css",
    "https://static.xx.fbcdn.net/rsrc.php/v5/yt/l/0",
    "cross/SnlSCjbtKRZ.css",
    "https://syndication.twitter.com/settings",
    "https://www.facebook.com/platform/plugin/page/logging/",
    "https://www.facebook.com/platform/plugin/tab/renderer/",
    "https://www.googletagmanager.com/gtag/js",
    "https://www.googletagmanager.com/gtm.js",
    "https://www.instagram.com/embed.js"
  ],
  "third_party_service_count": 15,
  "cookie_domains": [
    ".house.gov",
    ".swalwell.house.gov"
  ],
  "viewport_meta_tag": true,
  "cumulative_layout_shift": "0.47122709375",
  "largest_contentful_paint": "1354.1999999955297",
  "required_links_url": [
    "about",
    "privacy"
  ],
  "required_links_text": [
    "accessibility"
  ],
  "https_enforced": true,
  "hsts": false,
  "title": "Representative Swalwell |",
  "description": null,
  "keywords": null,
  "og_title": "Representative Swalwell",
  "og_description": null,
  "og_article_published": null,
  "og_article_modified": null,
  "og_image": "https://swalwell.house.gov/profiles/evo/assets/images/Seal_of_the_United_States_House_of_Representatives.png",
  "og_type": "website",
  "og_url": "http://swalwell.house.gov/home",
  "canonical_link": "http://swalwell.house.gov/",
  "language": "en",
  "language_link": "",
  "main_element_present": true,
  "robots_txt_detected": false,
  "robots_txt_url": "https://swalwell.house.gov/robots.txt",
  "robots_txt_status_code": 403,
  "robots_txt_media_type": "text/html",
  "robots_txt_filesize": null,
  "robots_txt_crawl_delay": null,
  "robots_txt_sitemap_locations": null,
  "sitemap_xml_detected": false,
  "sitemap_xml_url": "https://swalwell.house.gov/sitemap.xml",
  "sitemap_xml_status_code": 404,
  "sitemap_xml_media_type": "text/html",
  "sitemap_xml_filesize": null,
  "sitemap_xml_count": null,
  "sitemap_xml_pdf_count": null,
  "uswds_favicon": 0,
  "uswds_favicon_in_css": 0,
  "uswds_publicsans_font": 0,
  "uswds_inpage_css": 0,
  "uswds_usa_class_list": null,
  "uswds_banner_heres_how": false,
  "uswds_usa_classes": 0,
  "uswds_string": 0,
  "uswds_string_in_css": 0,
  "uswds_semantic_version": null,
  "uswds_version": 0,
  "uswds_count": 0,
  "www_scan_status": "dns_resolution_error",
  "www_url": null,
  "www_status_code": null,
  "www_title": null
}